wrench/__init__.py
wrench/_logging.py
wrench/backbone.py
wrench/basemodel.py
wrench/config.py
wrench/evaluation.py
wrench/layers.py
wrench/search.py
wrench/search_space.py
wrench/utils.py
wrench/version.py
wrench/classification/__init__.py
wrench/classification/astra.py
wrench/classification/denoise.py
wrench/classification/implyloss.py
wrench/classification/weasel.py
wrench/dataset/__init__.py
wrench/dataset/basedataset.py
wrench/dataset/dataset.py
wrench/dataset/graphdataset.py
wrench/dataset/seqdataset.py
wrench/dataset/torchdataset.py
wrench/dataset/utils.py
wrench/endmodel/__init__.py
wrench/endmodel/bert_model.py
wrench/endmodel/cosine.py
wrench/endmodel/end_model.py
wrench/endmodel/linear_model.py
wrench/endmodel/neural_model.py
wrench/labelmodel/__init__.py
wrench/labelmodel/dawid_skene.py
wrench/labelmodel/dependency_structure.py
wrench/labelmodel/epoxy.py
wrench/labelmodel/flyingsquid.py
wrench/labelmodel/generative_model.py
wrench/labelmodel/generative_model_src.py
wrench/labelmodel/gold.py
wrench/labelmodel/label_model_src.py
wrench/labelmodel/majority_voting.py
wrench/labelmodel/metal.py
wrench/labelmodel/naive_bayes.py
wrench/labelmodel/snorkel.py
wrench/metalearning/__init__.py
wrench/metalearning/learn_to_reweight.py
wrench/metalearning/meta_weight_net.py
wrench/semisupervisedlearning/__init__.py
wrench/semisupervisedlearning/meanteacher.py
wrench/semisupervisedlearning/utils.py
wrench/seq_endmodel/__init__.py
wrench/seq_endmodel/bert_crf_model.py
wrench/seq_endmodel/lstm_crf_model.py
wrench/seq_labelmodel/__init__.py
wrench/seq_labelmodel/chmm.py
wrench/seq_labelmodel/hmm.py
wrench/seq_labelmodel/seq_wrapper.py
wrench/seq_labelmodel/chmm_src/__init__.py
wrench/seq_labelmodel/chmm_src/CHMM/Data.py
wrench/seq_labelmodel/chmm_src/CHMM/Model.py
wrench/seq_labelmodel/chmm_src/CHMM/Train.py
wrench/seq_labelmodel/chmm_src/CHMM/__init__.py
wrench/seq_labelmodel/chmm_src/Src/Args.py
wrench/seq_labelmodel/chmm_src/Src/DataAssist.py
ws_benchmark-1.1.1.dist-info/LICENSE
ws_benchmark-1.1.1.dist-info/METADATA
ws_benchmark-1.1.1.dist-info/WHEEL
ws_benchmark-1.1.1.dist-info/top_level.txt
ws_benchmark-1.1.1.dist-info/RECORD
