Metadata-Version: 2.1
Name: ws-benchmark
Version: 1.1.1
Summary: a weak supervision learning benchmark
Home-page: https://github.com/JieyuZ2/wrench
Author: Jieyu Zhang
Author-email: jieyuzhang97@gmail.com
License: Apache License 2.0
Keywords: machine-learning ai weak-supervision
Platform: UNKNOWN
Classifier: Intended Audience :: Science/Research
Classifier: Topic :: Scientific/Engineering :: Information Analysis
Classifier: License :: OSI Approved :: Apache Software License
Classifier: Programming Language :: Python :: 3
Requires-Python: >=3.6
License-File: LICENSE
Requires-Dist: cytoolz (==0.11.0)
Requires-Dist: dill (==0.3.4)
Requires-Dist: flyingsquid (==0.0.0a0)
Requires-Dist: future (>=0.18.2)
Requires-Dist: higher (>=0.2.1)
Requires-Dist: typing-extensions (<=3.10.0.2,>=3.10.0.0)
Requires-Dist: torch (==1.9.0)
Requires-Dist: torchvision (==0.10.0)
Requires-Dist: tqdm (>=4.62.1)
Requires-Dist: transformers (<=4.7.0,>=4.6.1)
Requires-Dist: numpy (<=1.19.5,>=1.19.2)
Requires-Dist: snorkel (==0.9.7)
Requires-Dist: seqeval (==1.2.2)
Requires-Dist: scikit-learn (==0.24.2)
Requires-Dist: optuna (<=2.8.0,>=2.7.0)
Requires-Dist: pandas (>=1.1.5)
Requires-Dist: pillow (>=8.3.2)
Requires-Dist: sentence-transformers (==1.1.1)
Requires-Dist: openml (>=0.12.2)
Requires-Dist: cvxpy (<=1.1.15,>=1.1.13)
Requires-Dist: scipy (<=1.5.4,>=1.5.2)
Requires-Dist: faiss-gpu (>=1.7.1)
Requires-Dist: numbskull (==0.1.1)
Requires-Dist: numba (==0.43.0)
Requires-Dist: snorkel-metal (>=0.5.0)
Requires-Dist: spacy (<=3.1.5,>=3.1.2)
Requires-Dist: skweak (>=0.2.13)
Requires-Dist: networkx (==2.7)
